README.md
setup.py
iscraper/__init__.py
iscraper/client.py
iscraper_python.egg-info/PKG-INFO
iscraper_python.egg-info/SOURCES.txt
iscraper_python.egg-info/dependency_links.txt
iscraper_python.egg-info/requires.txt
iscraper_python.egg-info/top_level.txt