Metadata-Version: 2.1
Name: iscraper-python
Version: 1.0.2
Summary: Official Python SDK to consume https://iscraper.io LinkedIn data APIs.
Home-page: https://github.com/iscraper-project/iscraper-python/
Author: iScraper
Author-email: sales@iscraper.io
License: MIT
Platform: UNKNOWN
Requires-Python: >3.5.2
